santaslist/__init__.py
santaslist-0.0.7.dist-info/DESCRIPTION.rst
santaslist-0.0.7.dist-info/METADATA
santaslist-0.0.7.dist-info/RECORD
santaslist-0.0.7.dist-info/WHEEL
santaslist-0.0.7.dist-info/metadata.json
santaslist-0.0.7.dist-info/top_level.txt
test/__init__.py
test/test_SantasList.py
