Metadata-Version: 2.0
Name: santaslist
Version: 0.0.7
Summary: Helping santa
Home-page: https://github.com/obihann/Santaslist
Author: Jeff Hann
Author-email: jeffhann@gmail.com
License: UNKNOWN
Platform: UNKNOWN
Classifier: Development Status :: 3 - Alpha
Classifier: License :: OSI Approved :: GNU General Public License v2 or later (GPLv2+)
Classifier: Programming Language :: Python :: 3 :: Only
Classifier: Natural Language :: English
Classifier: Topic :: Utilities
Requires-Dist: pyyaml
